{"textQueryData":[{"example":"Find me the item where brand is Wallmart","query":"{\"brand\": \"Wallmart\"}"},{"example":"Find me the item where brand is Wallmart and Region is US","query":"{\"brand\": \"Wallmart\", \"regionUS\": \"true\"}"},{"example":"Find me the item which has store impact","query":"{\"storeImpact\":\"Yes\"}"},{"example":"Find me the item which doesnt have customer impact","query":"{\"customerImpact\": \"No\""},{"example":"Find me the item which has source as SAP ERP and target as Product Master DB","query":"{\"source\": \"SAP ERP\", \"target\": \"Product Master DB\""}],"params":"id, status, level, source, target, brand, regionNA, regionEU, regionAsia, regionJP, channel, context, interface, customerImpact, storeImpact, financeImpact, reportImpact, dcInventoryImpact, storeInventoryImpact, planningImpact, directIntegration, usingCP4i, interfaceFlow"}